a_cv2_easy_resize/LICENSE
a_cv2_easy_resize/README.MD
a_cv2_easy_resize/__init__.py
a_cv2_easy_resize/requirements.txt
a_cv2_easy_resize/thirdparty.json
a_cv2_easy_resize-0.10.dist-info/LICENSE.rst
a_cv2_easy_resize-0.10.dist-info/METADATA
a_cv2_easy_resize-0.10.dist-info/WHEEL
a_cv2_easy_resize-0.10.dist-info/top_level.txt
a_cv2_easy_resize-0.10.dist-info/RECORD
